{"notifications": [{"item": {"unreadCount": 0}, "type": "notificationTray"}], "meta": {"code": 200, "requestId": "58cb01b94434b95a2b643372"}, "response": {"confident": true, "venues": [{"referralId": "v-1489699257", "verified": false, "name": "Rm 340", "venueRatingBlacklisted": true, "venueChains": [], "hereNow": {"count": 0, "groups": [], "summary": "Nobody here"}, "specials": {"count": 0, "items": []}, "contact": {}, "hasPerk": false, "location": {"distance": 5835, "labeledLatLngs": [{"lat": 42.08794403076172, "lng": -78.43124389648438, "label": "display"}], "city": "Olean", "cc": "US", "country": "United States", "postalCode": "14760", "state": "NY", "formattedAddress": ["Olean, NY 14760", "United States"], "lat": 42.08794403076172, "lng": -78.43124389648438}, "beenHere": {"lastCheckinExpiredAt": 0}, "stats": {"tipCount": 0, "checkinsCount": 2, "usersCount": 1}, "id": "4f862ef8e4b02b69f31df7db", "categories": [{"pluralName": "Hospitals", "primary": true, "name": "Hospital", "shortName": "Hospital", "id": "4bf58dd8d48988d196941735", "icon": {"prefix": "https://ss3.4sqi.net/img/categories_v2/building/medical_", "suffix": ".png"}}]}, {"referralId": "v-1489699257", "verified": false, "name": "Out Patient Waiting Area - Olean General Hospital", "venueRatingBlacklisted": true, "venueChains": [], "hereNow": {"count": 0, "groups": [], "summary": "Nobody here"}, "specials": {"count": 0, "items": []}, "contact": {}, "hasPerk": false, "location": {"distance": 6214, "labeledLatLngs": [{"lat": 42.089965614171305, "lng": -78.42599010352178, "label": "display"}], "city": "Olean", "cc": "US", "country": "United States", "postalCode": "14760", "state": "NY", "formattedAddress": ["Main Street", "Olean, NY 14760", "United States"], "address": "Main Street", "lat": 42.089965614171305, "lng": -78.42599010352178}, "beenHere": {"lastCheckinExpiredAt": 0}, "stats": {"tipCount": 0, "checkinsCount": 14, "usersCount": 13}, "id": "4f16d375e4b0725ff0c8420d", "categories": [{"pluralName": "Hospitals", "primary": true, "name": "Hospital", "shortName": "Hospital", "id": "4bf58dd8d48988d196941735", "icon": {"prefix": "https://ss3.4sqi.net/img/categories_v2/building/medical_", "suffix": ".png"}}]}, {"referralId": "v-1489699257", "verified": false, "name": "Outpatient Lab", "venueRatingBlacklisted": true, "venueChains": [], "hereNow": {"count": 0, "groups": [], "summary": "Nobody here"}, "specials": {"count": 0, "items": []}, "contact": {}, "hasPerk": false, "location": {"distance": 20374, "labeledLatLngs": [{"lat": 41.960445, "lng": -78.659427, "label": "display"}], "city": "Bradford", "cc": "US", "country": "United States", "postalCode": "16701", "state": "PA", "formattedAddress": ["Bradford, PA 16701", "United States"], "lat": 41.960445, "lng": -78.659427}, "beenHere": {"lastCheckinExpiredAt": 0}, "stats": {"tipCount": 0, "checkinsCount": 5, "usersCount": 3}, "id": "506ef868e4b030d2b89e92b4", "categories": [{"pluralName": "Hospitals", "primary": true, "name": "Hospital", "shortName": "Hospital", "id": "4bf58dd8d48988d196941735", "icon": {"prefix": "https://ss3.4sqi.net/img/categories_v2/building/medical_", "suffix": ".png"}}]}, {"referralId": "v-1489699257", "verified": false, "name": "brmc surgical unit", "venueRatingBlacklisted": true, "venueChains": [], "hereNow": {"count": 0, "groups": [], "summary": "Nobody here"}, "specials": {"count": 0, "items": []}, "contact": {}, "hasPerk": false, "location": {"distance": 20189, "labeledLatLngs": [{"lat": 41.95602035522461, "lng": -78.64848327636719, "label": "display"}], "city": "Bradford", "cc": "US", "country": "United States", "postalCode": "16701", "state": "PA", "formattedAddress": ["Bradford, PA 16701", "United States"], "lat": 41.95602035522461, "lng": -78.64848327636719}, "beenHere": {"lastCheckinExpiredAt": 0}, "stats": {"tipCount": 0, "checkinsCount": 1, "usersCount": 1}, "id": "4f353250e4b0d361ebe84065", "categories": [{"pluralName": "Hospitals", "primary": true, "name": "Hospital", "shortName": "Hospital", "id": "4bf58dd8d48988d196941735", "icon": {"prefix": "https://ss3.4sqi.net/img/categories_v2/building/medical_", "suffix": ".png"}}]}, {"referralId": "v-1489699257", "verified": false, "name": "\ue322", "venueRatingBlacklisted": true, "venueChains": [], "hereNow": {"count": 0, "groups": [], "summary": "Nobody here"}, "specials": {"count": 0, "items": []}, "contact": {}, "hasPerk": false, "location": {"distance": 29116, "labeledLatLngs": [{"lat": 42.328753, "lng": -78.671251, "label": "display"}], "cc": "US", "country": "United States", "state": "New York", "formattedAddress": ["New York", "United States"], "lat": 42.328753, "lng": -78.671251}, "beenHere": {"lastCheckinExpiredAt": 0}, "stats": {"tipCount": 0, "checkinsCount": 0, "usersCount": 0}, "id": "4e1f87bee4cdf6859171d998", "categories": [{"pluralName": "Hospitals", "primary": true, "name": "Hospital", "shortName": "Hospital", "id": "4bf58dd8d48988d196941735", "icon": {"prefix": "https://ss3.4sqi.net/img/categories_v2/building/medical_", "suffix": ".png"}}]}, {"referralId": "v-1489699257", "verified": false, "name": "BRMC sleep lab", "venueRatingBlacklisted": true, "venueChains": [], "hereNow": {"count": 0, "groups": [], "summary": "Nobody here"}, "specials": {"count": 0, "items": []}, "contact": {}, "hasPerk": false, "location": {"distance": 20370, "labeledLatLngs": [{"lat": 41.96015144706024, "lng": -78.65888024798828, "label": "display"}], "city": "Bradford", "cc": "US", "country": "United States", "postalCode": "16701", "state": "PA", "formattedAddress": ["Bradford, PA 16701", "United States"], "lat": 41.96015144706024, "lng": -78.65888024798828}, "beenHere": {"lastCheckinExpiredAt": 0}, "stats": {"tipCount": 0, "checkinsCount": 4, "usersCount": 1}, "id": "4f6fd34be4b02781d60b44f3", "categories": [{"pluralName": "Hospitals", "primary": true, "name": "Hospital", "shortName": "Hospital", "id": "4bf58dd8d48988d196941735", "icon": {"prefix": "https://ss3.4sqi.net/img/categories_v2/building/medical_", "suffix": ".png"}}]}, {"referralId": "v-1489699257", "verified": false, "name": "Foothills Medical Group", "venueRatingBlacklisted": true, "venueChains": [], "hereNow": {"count": 0, "groups": [], "summary": "Nobody here"}, "specials": {"count": 0, "items": []}, "allowMenuUrlEdit": true, "contact": {"phone": "+18143687777", "formattedPhone": "+1 814-368-7777"}, "hasPerk": false, "location": {"distance": 20310, "labeledLatLngs": [{"lat": 41.96121979999999, "lng": -78.659452, "label": "display"}], "city": "Bradford", "cc": "US", "country": "United States", "postalCode": "16701", "state": "PA", "formattedAddress": ["106 - 116 Interstate Pkwy", "Bradford, PA 16701", "United States"], "address": "106 - 116 Interstate Pkwy", "lat": 41.96121979999999, "lng": -78.659452}, "beenHere": {"lastCheckinExpiredAt": 0}, "stats": {"tipCount": 0, "checkinsCount": 0, "usersCount": 0}, "id": "5554c744498e5cf634187f3c", "categories": [{"pluralName": "Hospitals", "primary": true, "name": "Hospital", "shortName": "Hospital", "id": "4bf58dd8d48988d196941735", "icon": {"prefix": "https://ss3.4sqi.net/img/categories_v2/building/medical_", "suffix": ".png"}}]}, {"referralId": "v-1489699257", "verified": false, "name": "olean general hospital outpatient surgery center", "venueRatingBlacklisted": true, "venueChains": [], "hereNow": {"count": 0, "groups": [], "summary": "Nobody here"}, "specials": {"count": 0, "items": []}, "contact": {}, "hasPerk": false, "location": {"distance": 6213, "labeledLatLngs": [{"lat": 42.09050222188519, "lng": -78.42587904988204, "label": "display"}], "city": "Olean", "cc": "US", "country": "United States", "postalCode": "14760", "state": "NY", "formattedAddress": ["Olean, NY 14760", "United States"], "lat": 42.09050222188519, "lng": -78.42587904988204}, "beenHere": {"lastCheckinExpiredAt": 0}, "stats": {"tipCount": 0, "checkinsCount": 4, "usersCount": 4}, "id": "50b36e6be4b02b5016a7122b", "categories": [{"pluralName": "Hospitals", "primary": true, "name": "Hospital", "shortName": "Hospital", "id": "4bf58dd8d48988d196941735", "icon": {"prefix": "https://ss3.4sqi.net/img/categories_v2/building/medical_", "suffix": ".png"}}]}, {"referralId": "v-1489699257", "verified": false, "name": "Surgical Associates: Nathaniel L. Graham, M.D., F.A.C.S.", "venueRatingBlacklisted": true, "venueChains": [], "url": "http://www.surgassoc.net", "hereNow": {"count": 0, "groups": [], "summary": "Nobody here"}, "specials": {"count": 0, "items": []}, "allowMenuUrlEdit": true, "contact": {"phone": "+18143687125", "formattedPhone": "+1 814-368-7125"}, "hasPerk": false, "location": {"distance": 20296, "labeledLatLngs": [{"lat": 41.962646, "lng": -78.661437, "label": "display"}], "city": "Bradford", "cc": "US", "country": "United States", "postalCode": "16701", "state": "PA", "formattedAddress": ["181 Interstate Pkwy", "Bradford, PA 16701", "United States"], "address": "181 Interstate Pkwy", "lat": 41.962646, "lng": -78.661437}, "beenHere": {"lastCheckinExpiredAt": 0}, "stats": {"tipCount": 0, "checkinsCount": 1, "usersCount": 1}, "id": "55569d5f498ede0742b86659", "categories": [{"pluralName": "Doctor's Offices", "primary": true, "name": "Doctor's Office", "shortName": "Doctor's Office", "id": "4bf58dd8d48988d177941735", "icon": {"prefix": "https://ss3.4sqi.net/img/categories_v2/building/medical_doctorsoffice_", "suffix": ".png"}}]}, {"referralId": "v-1489699257", "verified": false, "name": "Cuba Memorial Hospital", "venueRatingBlacklisted": true, "url": "http://www.cubamemorialhospital.com", "hereNow": {"count": 0, "groups": [], "summary": "Nobody here"}, "specials": {"count": 0, "items": []}, "venueChains": [], "contact": {"phone": "+15859682000", "formattedPhone": "+1 585-968-2000"}, "hasPerk": false, "location": {"distance": 21554, "labeledLatLngs": [{"lat": 42.213065202764966, "lng": -78.28796366561976, "label": "display"}], "city": "Cuba", "cc": "US", "country": "United States", "postalCode": "14727", "state": "NY", "formattedAddress": ["140 W Main St", "Cuba, NY 14727", "United States"], "address": "140 W Main St", "lat": 42.213065202764966, "lng": -78.28796366561976}, "beenHere": {"lastCheckinExpiredAt": 0}, "stats": {"tipCount": 1, "checkinsCount": 137, "usersCount": 54}, "id": "4dcd4d0c8877851243daeaa5", "categories": [{"pluralName": "Hospitals", "primary": true, "name": "Hospital", "shortName": "Hospital", "id": "4bf58dd8d48988d196941735", "icon": {"prefix": "https://ss3.4sqi.net/img/categories_v2/building/medical_", "suffix": ".png"}}]}, {"referralId": "v-1489699257", "verified": false, "name": "brmc diagnostic imaging", "venueRatingBlacklisted": true, "venueChains": [], "hereNow": {"count": 0, "groups": [], "summary": "Nobody here"}, "specials": {"count": 0, "items": []}, "contact": {}, "hasPerk": false, "location": {"distance": 20331, "labeledLatLngs": [{"lat": 41.96090714304763, "lng": -78.65936222023088, "label": "display"}], "city": "Bradford", "cc": "US", "country": "United States", "postalCode": "16701", "state": "PA", "formattedAddress": ["Bradford, PA 16701", "United States"], "lat": 41.96090714304763, "lng": -78.65936222023088}, "beenHere": {"lastCheckinExpiredAt": 0}, "stats": {"tipCount": 0, "checkinsCount": 15, "usersCount": 5}, "id": "4f15b64ce4b0d59e2434ab04", "categories": [{"pluralName": "Hospitals", "primary": true, "name": "Hospital", "shortName": "Hospital", "id": "4bf58dd8d48988d196941735", "icon": {"prefix": "https://ss3.4sqi.net/img/categories_v2/building/medical_", "suffix": ".png"}}]}, {"referralId": "v-1489699257", "verified": false, "name": "Bradford Regional Medical Center", "venueRatingBlacklisted": true, "venueChains": [], "hereNow": {"count": 0, "groups": [], "summary": "Nobody here"}, "specials": {"count": 0, "items": []}, "contact": {"phone": "+18143684143", "formattedPhone": "+1 814-368-4143"}, "hasPerk": false, "location": {"distance": 20318, "labeledLatLngs": [{"lat": 41.96089055142732, "lng": -78.65909630479813, "label": "display"}], "city": "Bradford", "cc": "US", "country": "United States", "postalCode": "16701", "state": "PA", "formattedAddress": ["116 Interstate Pkwy", "Bradford, PA 16701", "United States"], "address": "116 Interstate Pkwy", "lat": 41.96089055142732, "lng": -78.65909630479813}, "beenHere": {"lastCheckinExpiredAt": 0}, "stats": {"tipCount": 1, "checkinsCount": 975, "usersCount": 166}, "id": "4b6d05abf964a5206f632ce3", "categories": [{"pluralName": "Hospitals", "primary": true, "name": "Hospital", "shortName": "Hospital", "id": "4bf58dd8d48988d196941735", "icon": {"prefix": "https://ss3.4sqi.net/img/categories_v2/building/medical_", "suffix": ".png"}}]}, {"referralId": "v-1489699257", "verified": false, "name": "Olean General Hospital", "venueRatingBlacklisted": true, "venueChains": [], "url": "http://www.ogh.org", "hereNow": {"count": 0, "groups": [], "summary": "Nobody here"}, "specials": {"count": 0, "items": []}, "allowMenuUrlEdit": true, "contact": {"phone": "+17163732600", "formattedPhone": "+1 716-373-2600"}, "hasPerk": false, "location": {"distance": 6153, "labeledLatLngs": [{"lat": 42.08981, "lng": -78.42678, "label": "display"}], "city": "Olean", "cc": "US", "country": "United States", "postalCode": "14760", "state": "NY", "formattedAddress": ["515 Main St", "Olean, NY 14760", "United States"], "address": "515 Main St", "lat": 42.08981, "lng": -78.42678}, "beenHere": {"lastCheckinExpiredAt": 0}, "stats": {"tipCount": 3, "checkinsCount": 1429, "usersCount": 336}, "id": "4c52d443d797e21e9544207e", "categories": [{"pluralName": "Hospitals", "primary": true, "name": "Hospital", "shortName": "Hospital", "id": "4bf58dd8d48988d196941735", "icon": {"prefix": "https://ss3.4sqi.net/img/categories_v2/building/medical_", "suffix": ".png"}}]}]}}