{"notifications": [{"item": {"unreadCount": 0}, "type": "notificationTray"}], "meta": {"code": 200, "requestId": "58cb01d46a607125f10ec1aa"}, "response": {"confident": true, "venues": [{"referralId": "v-1489699284", "verified": false, "name": "L&D Ward SMC", "venueRatingBlacklisted": true, "venueChains": [], "hereNow": {"count": 0, "groups": [], "summary": "Nobody here"}, "specials": {"count": 0, "items": []}, "contact": {}, "hasPerk": false, "location": {"distance": 11810, "labeledLatLngs": [{"lat": 44.291428361288716, "lng": -75.54153443064429, "label": "display"}], "city": "Gouverneur", "cc": "US", "country": "United States", "state": "NY", "formattedAddress": ["Gouverneur, NY", "United States"], "lat": 44.291428361288716, "lng": -75.54153443064429}, "beenHere": {"lastCheckinExpiredAt": 0}, "stats": {"tipCount": 0, "checkinsCount": 1, "usersCount": 1}, "id": "4da6d8af8154fe28a8d8f456", "categories": [{"pluralName": "Hospitals", "primary": true, "name": "Hospital", "shortName": "Hospital", "id": "4bf58dd8d48988d196941735", "icon": {"prefix": "https://ss3.4sqi.net/img/categories_v2/building/medical_", "suffix": ".png"}}]}, {"referralId": "v-1489699284", "verified": false, "name": "EJ Noble Hospital", "venueRatingBlacklisted": true, "venueChains": [], "hereNow": {"count": 0, "groups": [], "summary": "Nobody here"}, "specials": {"count": 0, "items": []}, "contact": {}, "hasPerk": false, "location": {"distance": 19068, "labeledLatLngs": [{"lat": 44.33773972550508, "lng": -75.47444907813957, "label": "display"}], "city": "Gouverneur", "cc": "US", "country": "United States", "state": "NY", "formattedAddress": ["Gouverneur, NY", "United States"], "lat": 44.33773972550508, "lng": -75.47444907813957}, "beenHere": {"lastCheckinExpiredAt": 0}, "stats": {"tipCount": 0, "checkinsCount": 76, "usersCount": 23}, "id": "4de93620d1648c979646d6d8", "categories": [{"pluralName": "Hospitals", "primary": true, "name": "Hospital", "shortName": "Hospital", "id": "4bf58dd8d48988d196941735", "icon": {"prefix": "https://ss3.4sqi.net/img/categories_v2/building/medical_", "suffix": ".png"}}]}, {"referralId": "v-1489699284", "verified": true, "name": "Carthage Area Hospital", "venueRatingBlacklisted": true, "url": "http://www.carthagehospital.com/#Vgj0OO", "storeId": "", "hereNow": {"count": 0, "groups": [], "summary": "Nobody here"}, "specials": {"count": 0, "items": []}, "venueChains": [{"id": "556e5411bd6a82902e2859eb"}], "contact": {"phone": "+13154931000", "twitter": "carthagehosp", "formattedPhone": "+1 315-493-1000"}, "hasPerk": false, "location": {"distance": 23781, "labeledLatLngs": [{"lat": 43.986983, "lng": -75.5940619, "label": "display"}], "city": "Carthage", "cc": "US", "country": "United States", "postalCode": "13619", "state": "NY", "formattedAddress": ["1001 West St", "Carthage, NY 13619", "United States"], "address": "1001 West St", "lat": 43.986983, "lng": -75.5940619}, "beenHere": {"lastCheckinExpiredAt": 0}, "stats": {"tipCount": 1, "checkinsCount": 288, "usersCount": 109}, "id": "4f301bcde4b0ccb9159b8f81", "categories": [{"pluralName": "Hospitals", "primary": true, "name": "Hospital", "shortName": "Hospital", "id": "4bf58dd8d48988d196941735", "icon": {"prefix": "https://ss3.4sqi.net/img/categories_v2/building/medical_", "suffix": ".png"}}]}, {"referralId": "v-1489699284", "verified": false, "name": "River Hospital", "venueRatingBlacklisted": true, "venueChains": [], "hereNow": {"count": 0, "groups": [], "summary": "Nobody here"}, "specials": {"count": 0, "items": []}, "contact": {}, "hasPerk": false, "location": {"distance": 28628, "labeledLatLngs": [{"lat": 44.33758141245669, "lng": -75.92010564163671, "label": "display"}], "city": "Alexandria Bay", "cc": "US", "country": "United States", "postalCode": "13607", "state": "NY", "formattedAddress": ["4 Fuller St", "Alexandria Bay, NY 13607", "United States"], "address": "4 Fuller St", "lat": 44.33758141245669, "lng": -75.92010564163671}, "beenHere": {"lastCheckinExpiredAt": 0}, "stats": {"tipCount": 0, "checkinsCount": 153, "usersCount": 39}, "id": "4c5ad1462091a593fd3b60d0", "categories": [{"pluralName": "Hospitals", "primary": true, "name": "Hospital", "shortName": "Hospital", "id": "4bf58dd8d48988d196941735", "icon": {"prefix": "https://ss3.4sqi.net/img/categories_v2/building/medical_", "suffix": ".png"}}]}, {"referralId": "v-1489699284", "verified": false, "name": "Guthrie Clinic", "venueRatingBlacklisted": true, "venueChains": [], "hereNow": {"count": 0, "groups": [], "summary": "Nobody here"}, "specials": {"count": 0, "items": []}, "allowMenuUrlEdit": true, "contact": {}, "hasPerk": false, "location": {"distance": 22050, "labeledLatLngs": [{"lat": 44.05988166075074, "lng": -75.81172957203707, "label": "display"}], "city": "Fort Drum", "cc": "US", "country": "United States", "postalCode": "13603", "state": "NY", "formattedAddress": ["Mt Belvedere Blvd", "Fort Drum, NY 13603", "United States"], "address": "Mt Belvedere Blvd", "lat": 44.05988166075074, "lng": -75.81172957203707}, "beenHere": {"lastCheckinExpiredAt": 0}, "stats": {"tipCount": 6, "checkinsCount": 1228, "usersCount": 199}, "id": "4c23a586a852c92865d7e16c", "categories": [{"pluralName": "Medical Centers", "primary": true, "name": "Medical Center", "shortName": "Medical", "id": "4bf58dd8d48988d104941735", "icon": {"prefix": "https://ss3.4sqi.net/img/categories_v2/building/medical_", "suffix": ".png"}}]}, {"referralId": "v-1489699284", "verified": false, "name": "Carthage Hosp. X-Ray Dept", "venueRatingBlacklisted": true, "venueChains": [], "hereNow": {"count": 0, "groups": [], "summary": "Nobody here"}, "specials": {"count": 0, "items": []}, "contact": {}, "hasPerk": false, "location": {"distance": 23742, "labeledLatLngs": [{"lat": 43.987342, "lng": -75.593871, "label": "display"}], "city": "Carthage", "cc": "US", "country": "United States", "state": "NY", "formattedAddress": ["Carthage, NY", "United States"], "lat": 43.987342, "lng": -75.593871}, "beenHere": {"lastCheckinExpiredAt": 0}, "stats": {"tipCount": 0, "checkinsCount": 2, "usersCount": 2}, "id": "52bc6ff5498ed57baab18f1f", "categories": [{"pluralName": "Hospitals", "primary": true, "name": "Hospital", "shortName": "Hospital", "id": "4bf58dd8d48988d196941735", "icon": {"prefix": "https://ss3.4sqi.net/img/categories_v2/building/medical_", "suffix": ".png"}}]}, {"referralId": "v-1489699284", "verified": false, "name": "Andrew LaFrance, FNP", "venueRatingBlacklisted": true, "venueChains": [], "url": "https://www.cphospital.org/providers/andrew-lafrance", "hereNow": {"count": 0, "groups": [], "summary": "Nobody here"}, "specials": {"count": 0, "items": []}, "allowMenuUrlEdit": true, "contact": {"phone": "+13155621055", "formattedPhone": "+1 315-562-1055"}, "hasPerk": false, "location": {"distance": 32313, "labeledLatLngs": [{"lat": 44.325609594813855, "lng": -75.25124499262506, "label": "display"}], "city": "Edwards", "cc": "US", "country": "United States", "postalCode": "13635", "state": "NY", "formattedAddress": ["8 Church Street", "Edwards, NY 13635", "United States"], "address": "8 Church Street", "lat": 44.325609594813855, "lng": -75.25124499262506}, "beenHere": {"lastCheckinExpiredAt": 0}, "stats": {"tipCount": 0, "checkinsCount": 0, "usersCount": 0}, "id": "57a29c4d498e6a2fd86e0e22", "categories": [{"pluralName": "Doctor's Offices", "primary": true, "name": "Doctor's Office", "shortName": "Doctor's Office", "id": "4bf58dd8d48988d177941735", "icon": {"prefix": "https://ss3.4sqi.net/img/categories_v2/building/medical_doctorsoffice_", "suffix": ".png"}}]}, {"referralId": "v-1489699284", "verified": false, "name": "Paul watson", "venueRatingBlacklisted": true, "venueChains": [], "hereNow": {"count": 0, "groups": [], "summary": "Nobody here"}, "specials": {"count": 0, "items": []}, "contact": {"phone": "+12127595006", "formattedPhone": "+1 212-759-5006"}, "hasPerk": false, "location": {"distance": 30482, "labeledLatLngs": [{"lat": 44.185943093595036, "lng": -75.23525476455688, "label": "display"}], "city": "New York", "cc": "US", "country": "United States", "postalCode": "10022", "state": "NY", "formattedAddress": ["133 E 58th St Ste 902", "New York, NY 10022", "United States"], "address": "133 E 58th St Ste 902", "lat": 44.185943093595036, "lng": -75.23525476455688}, "beenHere": {"lastCheckinExpiredAt": 0}, "stats": {"tipCount": 0, "checkinsCount": 0, "usersCount": 0}, "id": "4fc0708e77164a4501d064e6", "categories": [{"pluralName": "Hospitals", "primary": true, "name": "Hospital", "shortName": "Hospital", "id": "4bf58dd8d48988d196941735", "icon": {"prefix": "https://ss3.4sqi.net/img/categories_v2/building/medical_", "suffix": ".png"}}]}, {"referralId": "v-1489699284", "verified": false, "name": "Guthrie Pharmacy", "venueRatingBlacklisted": true, "venueChains": [], "hereNow": {"count": 0, "groups": [], "summary": "Nobody here"}, "specials": {"count": 0, "items": []}, "allowMenuUrlEdit": true, "contact": {"phone": "+13157723696", "formattedPhone": "+1 315-772-3696"}, "hasPerk": false, "location": {"distance": 22063, "labeledLatLngs": [{"lat": 44.05960281790125, "lng": -75.81158201044458, "label": "display"}], "city": "Fort Drum", "cc": "US", "country": "United States", "postalCode": "13602", "state": "NY", "formattedAddress": ["Fort Drum, NY 13602", "United States"], "lat": 44.05960281790125, "lng": -75.81158201044458}, "beenHere": {"lastCheckinExpiredAt": 0}, "stats": {"tipCount": 2, "checkinsCount": 261, "usersCount": 72}, "id": "4c598931d3aee21e35636855", "categories": [{"pluralName": "Hospitals", "primary": true, "name": "Hospital", "shortName": "Hospital", "id": "4bf58dd8d48988d196941735", "icon": {"prefix": "https://ss3.4sqi.net/img/categories_v2/building/medical_", "suffix": ".png"}}]}, {"referralId": "v-1489699284", "verified": false, "name": "Heli Pad/ Washington St.", "venueRatingBlacklisted": true, "venueChains": [], "hereNow": {"count": 0, "groups": [], "summary": "Nobody here"}, "specials": {"count": 0, "items": []}, "contact": {}, "hasPerk": false, "location": {"distance": 25229, "labeledLatLngs": [{"lat": 43.974159370490995, "lng": -75.59022848868, "label": "display"}], "city": "Carthage", "cc": "US", "country": "United States", "postalCode": "13619", "state": "NY", "formattedAddress": ["Carthage, NY 13619", "United States"], "lat": 43.974159370490995, "lng": -75.59022848868}, "beenHere": {"lastCheckinExpiredAt": 0}, "stats": {"tipCount": 0, "checkinsCount": 4, "usersCount": 2}, "id": "4fcd25ede4b06828147051d5", "categories": [{"pluralName": "Hospitals", "primary": true, "name": "Hospital", "shortName": "Hospital", "id": "4bf58dd8d48988d196941735", "icon": {"prefix": "https://ss3.4sqi.net/img/categories_v2/building/medical_", "suffix": ".png"}}]}]}}